PicoAirQuality.py
KitronikPicoSmartAirQuality-1.0.2.dist-info/LICENSE
KitronikPicoSmartAirQuality-1.0.2.dist-info/METADATA
KitronikPicoSmartAirQuality-1.0.2.dist-info/WHEEL
KitronikPicoSmartAirQuality-1.0.2.dist-info/top_level.txt
KitronikPicoSmartAirQuality-1.0.2.dist-info/RECORD
