Metadata-Version: 2.1
Name: KitronikPicoSmartAirQuality
Version: 1.0.2
Summary: Kitronik Air Quality Datalogging Board for Pico
Keywords: micropython,package
Classifier: Programming Language :: Python :: Implementation :: MicroPython
License-File: LICENSE
